MultiSignals/MultiSignals.py
MultiSignals/__init__.py
multisignals-0.1.0.dist-info/licenses/LICENSE
multisignals-0.1.0.dist-info/METADATA
multisignals-0.1.0.dist-info/WHEEL
multisignals-0.1.0.dist-info/top_level.txt
multisignals-0.1.0.dist-info/RECORD
