Metadata-Version: 2.4
Name: MultiSignals
Version: 0.1.0
Summary: Esta libreria permite crear y gestionar variables y eventos en multiples scripts a la vez
Author-email: Facundo Efimenco Chiappe <facu22251@gmail.com>
Project-URL: Homepage, https://github.com/facu-programer/MultiSignals/
Project-URL: Bug Tracker, https://github.com/facu-programer/MultiSignals/issues
Keywords: vars,event,signals,python,global,shared,variables
Classifier: Programming Language :: Python :: 3
Classifier: Operating System :: OS Independent
Classifier: License :: Other/Proprietary License
Requires-Python: >=3.7
License-File: LICENSE
Requires-Dist: requests
Requires-Dist: flask
Dynamic: license-file
